nemo_evaluator_launcher/__init__.py
nemo_evaluator_launcher/package_info.py
nemo_evaluator_launcher/api/__init__.py
nemo_evaluator_launcher/api/functional.py
nemo_evaluator_launcher/api/types.py
nemo_evaluator_launcher/api/utils.py
nemo_evaluator_launcher/cli/__init__.py
nemo_evaluator_launcher/cli/export.py
nemo_evaluator_launcher/cli/info.py
nemo_evaluator_launcher/cli/kill.py
nemo_evaluator_launcher/cli/logs.py
nemo_evaluator_launcher/cli/ls_runs.py
nemo_evaluator_launcher/cli/ls_task.py
nemo_evaluator_launcher/cli/ls_tasks.py
nemo_evaluator_launcher/cli/main.py
nemo_evaluator_launcher/cli/run.py
nemo_evaluator_launcher/cli/status.py
nemo_evaluator_launcher/cli/version.py
nemo_evaluator_launcher/common/__init__.py
nemo_evaluator_launcher/common/execdb.py
nemo_evaluator_launcher/common/helpers.py
nemo_evaluator_launcher/common/logging_utils.py
nemo_evaluator_launcher/common/mapping.py
nemo_evaluator_launcher/common/printing_utils.py
nemo_evaluator_launcher/common/container_metadata/__init__.py
nemo_evaluator_launcher/common/container_metadata/intermediate_repr.py
nemo_evaluator_launcher/common/container_metadata/loading.py
nemo_evaluator_launcher/common/container_metadata/registries.py
nemo_evaluator_launcher/common/container_metadata/utils.py
nemo_evaluator_launcher/configs/__init__.py
nemo_evaluator_launcher/configs/default.yaml
nemo_evaluator_launcher/configs/deployment/generic.yaml
nemo_evaluator_launcher/configs/deployment/nim.yaml
nemo_evaluator_launcher/configs/deployment/none.yaml
nemo_evaluator_launcher/configs/deployment/sglang.yaml
nemo_evaluator_launcher/configs/deployment/trtllm.yaml
nemo_evaluator_launcher/configs/deployment/vllm.yaml
nemo_evaluator_launcher/configs/execution/local.yaml
nemo_evaluator_launcher/configs/execution/lepton/default.yaml
nemo_evaluator_launcher/configs/execution/slurm/default.yaml
nemo_evaluator_launcher/executors/__init__.py
nemo_evaluator_launcher/executors/base.py
nemo_evaluator_launcher/executors/registry.py
nemo_evaluator_launcher-0.1.67.dist-info/licenses/LICENSE
nemo_evaluator_launcher-0.1.67.dist-info/METADATA
nemo_evaluator_launcher-0.1.67.dist-info/WHEEL
nemo_evaluator_launcher-0.1.67.dist-info/entry_points.txt
nemo_evaluator_launcher-0.1.67.dist-info/top_level.txt
nemo_evaluator_launcher-0.1.67.dist-info/RECORD
