Metadata-Version: 2.4
Name: nemo-evaluator-launcher
Version: 0.1.67
Summary: Launcher for the evaluations provided by NeMo Evaluator containers with different runtime backends
Author: NVIDIA
Author-email: nemo-toolkit@nvidia.com
Maintainer: NVIDIA
Maintainer-email: nemo-toolkit@nvidia.com
License: 
Project-URL: homepage, https://github.com/NVIDIA-NeMo/Evaluator
Project-URL: repository, https://github.com/NVIDIA-NeMo/Evaluator/packages/nemo-evaluator-launcher
Keywords: deep learning,evaluations,machine learning,gpu,NLP,pytorch,torch
Requires-Python: <3.14,>=3.10
License-File: LICENSE
Requires-Dist: hydra-core<2.0.0,>=1.3.2
Requires-Dist: jinja2<4.0.0,>=3.1.6
Requires-Dist: leptonai>=0.25.0
Requires-Dist: nemo-evaluator
Requires-Dist: pyyaml>=6.0.0
Requires-Dist: requests>=2.32.4
Requires-Dist: simple-parsing<0.2.0,>=0.1.7
Requires-Dist: structlog<26.0.0,>=25.4.0
Requires-Dist: tabulate<0.10.0,>=0.9.0
Requires-Dist: tomli<3.0.0,>=2.0.0; python_version < "3.11"
Provides-Extra: mlflow
Requires-Dist: mlflow>=2.8.0; extra == "mlflow"
Provides-Extra: wandb
Requires-Dist: wandb>=0.15.0; extra == "wandb"
Provides-Extra: gsheets
Requires-Dist: gspread>=5.0.0; extra == "gsheets"
Provides-Extra: exporters
Requires-Dist: mlflow; extra == "exporters"
Requires-Dist: wandb; extra == "exporters"
Requires-Dist: gsheets; extra == "exporters"
Provides-Extra: all
Requires-Dist: mlflow; extra == "all"
Requires-Dist: wandb; extra == "all"
Requires-Dist: gsheets; extra == "all"
Dynamic: license-file
